pyparcels/features/feature_utils.py
pyparcels/parcels/parcels_utils.py
pyparcels/utils/__init__.py
pyparcels/utils/utils.py
pyparcels/versioning/versioning_utils.py
pyparcels-1.4.2.dist-info/METADATA
pyparcels-1.4.2.dist-info/WHEEL
pyparcels-1.4.2.dist-info/license.txt
pyparcels-1.4.2.dist-info/top_level.txt
pyparcels-1.4.2.dist-info/RECORD
