Metadata-Version: 2.1
Name: pyparcels
Version: 1.4.2
Summary: Helper functions for simplifying parcel fabric workflows with the ArcGIS Python API
Home-page: https://github.com/kgalliher/arcgis-pythonapi/
Author: Ken Galliher
Author-email: kgalliher092@gmail.com
Project-URL: Bug Reports, https://github.com/kgalliher/arcgis-pythonapi/issues/
Project-URL: Source, https://github.com/kgalliher/arcgis-pythonapi/
Keywords: arcgis python api,parcels,development
Classifier: Development Status :: 3 - Alpha
Classifier: Intended Audience :: Developers
Classifier: Topic :: Software Development :: Build Tools
Classifier: License :: OSI Approved :: MIT License
Classifier: Programming Language :: Python :: 3
Classifier: Programming Language :: Python :: 3.6
Classifier: Programming Language :: Python :: 3.7
Classifier: Programming Language :: Python :: 3.8
Classifier: Programming Language :: Python :: 3.9
Classifier: Programming Language :: Python :: 3.10
Classifier: Programming Language :: Python :: 3 :: Only
Requires-Python: >=3.6, <4
License-File: license.txt
